<?xml version="1.0" encoding="utf-8"?>
<openerp>
    <data>
		<record id="ir_cron_tmerp_listing_action" model="ir.cron">
            <field name="name">Trademe Listing Schedule</field>
            <field name="interval_number">10</field>
            <field name="interval_type">minutes</field>
            <field name="numbercall">-1</field>
            <field eval="False" name="doall"/>
            <field eval="'tmerp.action.listing'" name="model"/>
            <field eval="'_fetch_members_listing'" name="function"/>
            <field eval="'()'" name="args"/>
		</record>
		<record id="ir_cron_tmerp_questions_action" model="ir.cron">
            <field name="name">Trademe Listing Question Schedule</field>
            <field name="interval_number">10</field>
            <field name="interval_type">minutes</field>
            <field name="numbercall">-1</field>
            <field eval="False" name="doall"/>
            <field eval="'tmerp.action.listing'" name="model"/>
            <field eval="'_fetch_un_questions'" name="function"/>
            <field eval="'()'" name="args"/>
		</record>
    </data>
	
</openerp>