<?xml version="1.0" encoding="UTF-8"?>
<!-- vim:fdl=1: -->
<templates>
    <t t-extend="Orderline">
        <t t-jquery=".product-name" t-operation="replace">
            <span class="product-name">
                <t t-esc="line.get_sequence()"/>.
                <t t-esc="line.get_product().display_name"/>
            </span>
        </t>
    </t>

    <t t-extend="OrderWidget">
        <t t-jquery=".summary" t-operation="replace">
            <div class="summary clearfix">
                <div t-attf-class="line #{orderlines.length === 0 ? 'empty' : ''}">
                    <div class='entry total'>
                        <table>
                            <tr>
                                <td><span>Total Quantity: </span><span class="quantity">0</span></td>
                                <td>Unit(s).</td>
                                <td><span>Total: </span> <span class="value">0.00€</span></td>
                            </tr>
                            <tr>
                                <td></td>
                                <td></td>
                                <td><div class='subentry'>Taxes: <span class="value">0.00€</span></div></td>
                            </tr>
                        </table>
                    </div>
                </div>
            </div>
        </t>
    </t>

</templates>
